[{"name": "", "free_returns": false, "items_sold": null, "items_status": null, "items_shipping": null, "price": null}, {"name": "Men Army Cap Cadet Military Patrol Castro Hat Golf Driving Summer Baseball Hats", "free_returns": false, "items_sold": null, "items_status": "Brand New", "items_shipping": 0, "price": 939}, {"name": "Men's Carhartt Acrylic Watch Hat Winter Beanie Knit Cap Women Warm Stocking Hat", "free_returns": true, "items_sold": null, "items_status": "Brand New", "items_shipping": 0, "price": 1279}, {"name": "Men Women Face Mask Winter Warm Ski Cap 3Hole Balaclava Beanie Hat Hood Tactical", "free_returns": true, "items_sold": null, "items_status": "Brand New", "items_shipping": 0, "price": 895}, {"name": "Plain Baseball Cap Strapback Adjustable Solid Blank Hat Polo Style Visor Caps", "free_returns": true, "items_sold": null, "items_status": "Brand New", "items_shipping": 0, "price": 675}, {"name": "Plain Trucker Hat Mesh Back Snapback Baseball Cap Solid Visor Blank Hats Caps", "free_returns": true, "items_sold": 3552, "items_status": "Brand New", "items_shipping": null, "price": 795}, {"name": "Ski Mask Winter Hat 1 One Hole Balaclava Hood Beanie Hats Tactical Warm Cap", "free_returns": true, "items_sold": null, "items_status": "Brand New", "items_shipping": 0, "price": 899}, {"name": "3 Hole Full Face Mask Ski Mask Winter Cap Balaclava Outdoor Beanie Tactical Hat", "free_returns": true, "items_sold": 6289, "items_status": "Brand New", "items_shipping": null, "price": 795}, {"name": "Beanie Hat Cap Solid Plain Knit Ski Skull Cuff Winter Warm Slouchy Men Women", "free_returns": true, "items_sold": 10000, "items_status": "Brand New", "items_shipping": null, "price": 695}, {"name": "Black Military Tactical Skull Cap Winter Warm Fleece Windproof Ski Beanie Hats", "free_returns": true, "items_sold": null, "items_status": "Brand New", "items_shipping": 0, "price": 799}, {"name": "Mens Womens Winter Thermal Fleece Lined Insulated Knit Beanie Hat Cuff Cap Ski", "free_returns": false, "items_sold": null, "items_status": "Brand New", "items_shipping": null, "price": 799}, {"name": "Plain Baseball Cap Solid Blank Curved Visor Hat Ball Army Men Women loop Wool VC", "free_returns": true, "items_sold": 10000, "items_status": "Brand New", "items_shipping": 0, "price": 679}, {"name": "FLEXFIT Classic ORIGINAL 6-Panel Fitted Baseball Cap HAT S/M & L/XL All Colors!", "free_returns": true, "items_sold": null, "items_status": "Brand New", "items_shipping": 0, "price": 1297}, {"name": "EM Herringbone Ivy Hat Wool Stripe Gatsby Cap Golf Driving Flat Cabbie Newsboy", "free_returns": true, "items_sold": 521, "items_status": "Brand New", "items_shipping": null, "price": 1399}, {"name": "Men Hats Winter Warm Knit Cap Ski Hat Beanie Fleece Snow Caps Skull Cuff Women", "free_returns": false, "items_sold": null, "items_status": "Brand New", "items_shipping": null, "price": 693}, {"name": "CAP MILITARY BASEBALL ARMY NAVY ~ Cotton Flag Boonie Golf Plaid Hat", "free_returns": true, "items_sold": null, "items_status": "Brand New", "items_shipping": 0, "price": 1095}, {"name": "1Day- Men's Carhartt Acrylic Watch Hat Beanie Winter Knit Cap Authentic A18", "free_returns": true, "items_sold": 214, "items_status": "Brand New", "items_shipping": 0, "price": 1190}, {"name": "Men Women Winter Aviator Bomber Hat Trooper Ear Flap Ski Trapper Face Mask Cap", "free_returns": true, "items_sold": null, "items_status": "Brand New", "items_shipping": 0, "price": 1197}, {"name": "Flexfit Delta Cap FF180", "free_returns": false, "items_sold": 324, "items_status": "Brand New", "items_shipping": 0, "price": 1249}, {"name": "NEW BMW Cap Baseball Stylish Hat Car Adults Golf Embroidery Black White Snapback", "free_returns": false, "items_sold": null, "items_status": "Brand New", "items_shipping": 0, "price": 845}, {"name": "Snapback Hat Flat Baseball Cap Trucker Solid Plain Blank Men Hip Hop Army CS", "free_returns": true, "items_sold": 5008, "items_status": "Brand New", "items_shipping": null, "price": 895}, {"name": "FLEXFIT Original Twill Fitted CLASSIC Hat Plain Blank 6-Panel Cap", "free_returns": true, "items_sold": null, "items_status": "Brand New", "items_shipping": 0, "price": 1395}, {"name": "Snapback Hat Classic Hip Hop Style Flat Brim Baseball Cap Solid Color Blank Hats", "free_returns": true, "items_sold": null, "items_status": "Brand New", "items_shipping": 0, "price": 796}, {"name": "Trucker Hat Mesh Baseball Cap Snapback Adjustable Hip Hop Flat Solid Plain Men", "free_returns": true, "items_sold": 3402, "items_status": "Brand New", "items_shipping": null, "price": 795}, {"name": "Premium Solid Fitted Cap Baseball Cap Hat, Flat Bill / Brim NEW", "free_returns": false, "items_sold": 1318, "items_status": "Brand New", "items_shipping": 0, "price": 1199}, {"name": "Washed Cotton Baseball Cap Adjustable Hat Polo Style Plain Solid Blank Dad Men", "free_returns": true, "items_sold": 3848, "items_status": "Brand New", "items_shipping": null, "price": 745}, {"name": "PUMA Men's Force 2.0 Stretch Fit Cap", "free_returns": true, "items_sold": 0, "items_status": "Brand New", "items_shipping": 0, "price": 999}, {"name": "Bucket Hat Boonie Visor Hunting Fishing Outdoor Summer Cap Unisex 100% Cotton", "free_returns": true, "items_sold": 2241, "items_status": "Brand New", "items_shipping": 0, "price": 874}, {"name": "Richardson 112 Trucker Ball Cap Meshback Hat Snapback Cap Trucker Hat Cap - OSFM", "free_returns": false, "items_sold": null, "items_status": "Brand New", "items_shipping": 0, "price": 1095}, {"name": "Men Women Hats Winter Warm Knit Cap Ski Hat Beanie Fleece Snow Caps Skull Cuff ", "free_returns": false, "items_sold": null, "items_status": "Brand New", "items_shipping": null, "price": 694}, {"name": "Women's Men Knit Slouchy Baggy Beanie Oversize Winter Hat Ski Fleece Slouchy Cap", "free_returns": true, "items_sold": null, "items_status": "Brand New", "items_shipping": null, "price": 799}, {"name": "Front 3D Embroidered Logo Baseball Cap Flat Brim Snapback Men Outdoor Sports Hat", "free_returns": false, "items_sold": null, "items_status": "Brand New", "items_shipping": 99, "price": 1399}, {"name": "Cuff Beanie Knit Hat Winter Cap Slouchy Skull Ski Solid Men Women Plain Baggy", "free_returns": true, "items_sold": 4639, "items_status": "Brand New", "items_shipping": null, "price": 695}, {"name": "Beanie Cap Plain Knit Ski Skull Hat Cuff Winter Solid Warm Slouchy Men Women Hat", "free_returns": true, "items_sold": 3165, "items_status": "Brand New", "items_shipping": null, "price": 695}, {"name": "Trucker Hat Foam Mesh Baseball Cap Adjustable Snapback Solid Plain Men Hats", "free_returns": true, "items_sold": 173, "items_status": "New (Other)", "items_shipping": 0, "price": 789}, {"name": "Hot item! CC Beanie New Women's Knit Slouchy Thick Cap Hat Unisex Solid Color", "free_returns": true, "items_sold": null, "items_status": "Brand New", "items_shipping": 0, "price": 949}, {"name": "Solid Plain Baseball Cap Trucker  Camo Blank Hat Ball Men Women Adjustable VC", "free_returns": true, "items_sold": 3275, "items_status": "Brand New", "items_shipping": null, "price": 674}, {"name": "Solid Cotton Gatsby Cap Mens Ivy Hat Golf Driving Summer Sun Flat Cabbie Newsboy", "free_returns": true, "items_sold": 4117, "items_status": "Brand New", "items_shipping": null, "price": 1399}, {"name": "PUMA Men's Dillon Stretchfit Cap", "free_returns": true, "items_sold": 0, "items_status": "Brand New", "items_shipping": 0, "price": 999}, {"name": "3Pcs Set Winter Knit Beanie Hat Scarf Touch Screen Ski Gloves Cap Warm Men Women", "free_returns": true, "items_sold": null, "items_status": "Brand New", "items_shipping": 0, "price": 1299}, {"name": "Men's Fur Ear Flap Winter Hat Trapper Bomber Aviator Warm Baseball Cap Face Mask", "free_returns": true, "items_sold": null, "items_status": "Brand New", "items_shipping": null, "price": 1099}, {"name": "Men Cap Army Hat Cadet Castro Military Patrol Baseball Summer Camo Camouflage", "free_returns": true, "items_sold": null, "items_status": "Brand New", "items_shipping": 0, "price": 899}, {"name": "Cable Knit Beanie Ski Cap Skull Hat Warm Solid Winter Cuff New Blank Heather", "free_returns": false, "items_sold": 530, "items_status": "Brand New", "items_shipping": 0, "price": 995}, {"name": "the Original Flexfit Fitted Baseball Hat Wooly Combed Twill Cap Flex Fit 6277", "free_returns": true, "items_sold": null, "items_status": "New (Other)", "items_shipping": 100, "price": 1299}, {"name": "Vintage Leather Solid Gatsby Cap Mens Ivy Hat Golf Driving Flat Cabbie Newsboy", "free_returns": true, "items_sold": 551, "items_status": "Brand New", "items_shipping": null, "price": 1499}, {"name": "Visor Sun Hat Golf Tennis Beach Mens Cap Adjustable Summer Plain Colors Polo ", "free_returns": true, "items_sold": null, "items_status": "Brand New", "items_shipping": 0, "price": 695}, {"name": "Bass Pro Shops Hat Mesh Adjustable SnapBack Trucker Baseball Fishing Outdoor Cap", "free_returns": true, "items_sold": null, "items_status": "Brand New", "items_shipping": 0, "price": 1699}, {"name": "MEXICAN MEXICO Hat Hecho En Mexico Eagle Aguila Snapback Flat Bill Baseball Cap", "free_returns": true, "items_sold": 553, "items_status": "Brand New", "items_shipping": null, "price": 1285}, {"name": "Men Women Army Cap Cadet Military Patrol Castro Hat Golf Driving Summer Baseball", "free_returns": false, "items_sold": null, "items_status": "Brand New", "items_shipping": null, "price": 695}, {"name": "Newsboy Ivy Ascot Cabbie Hat Cap Plaid Wool Herringbone Gatsby Golf Driving", "free_returns": false, "items_sold": 172, "items_status": "Brand New", "items_shipping": 0, "price": 1299}, {"name": "BDU Fitted Army Cadet Military Cap Hat Patrol Castro Combat Hunting", "free_returns": true, "items_sold": 778, "items_status": "Brand New", "items_shipping": null, "price": 1197}, {"name": "PUMA Men's Decimal 2.0 Stretch Fit Cap", "free_returns": true, "items_sold": 0, "items_status": "Brand New", "items_shipping": 0, "price": 999}, {"name": "NEW Mens Jordan Baseball Cap Snapback Hat Multi Color Adjustable", "free_returns": false, "items_sold": null, "items_status": "Brand New", "items_shipping": 0, "price": 1395}, {"name": "Nike Beanie Team Beanie Cuffed Warm Winter Dri-Fit Acrylic Hat Cap CW6117", "free_returns": true, "items_sold": null, "items_status": "Brand New", "items_shipping": 0, "price": 1699}, {"name": "Original Flexfit Fitted Baseball Hat Wooly Combed Twill Cap Blank Flex Fit 6277", "free_returns": false, "items_sold": 836, "items_status": "New (Other)", "items_shipping": 0, "price": 1295}, {"name": "Solid Cotton Gatsby Cap Mens Denim Hat Golf Driving Summer Sun Cabbie Newsboy", "free_returns": false, "items_sold": 412, "items_status": "Brand New", "items_shipping": 0, "price": 1299}, {"name": "Cotton Baseball Cap Ball Dad Hat Adjustable Plain Solid Washed Men Washed PC", "free_returns": true, "items_sold": 10000, "items_status": "Brand New", "items_shipping": null, "price": 899}, {"name": "Wool Corduroy Gatsby Cap Ivy Hat Golf Driving Winter Sun Flat Cabbie Newsboy", "free_returns": true, "items_sold": 99, "items_status": "Brand New", "items_shipping": null, "price": 1399}, {"name": "Plain Baseball Cap Solid Color Blank Army Hat Ball Men Women Hook-N-Loop VC wool", "free_returns": true, "items_sold": 9592, "items_status": "Brand New", "items_shipping": null, "price": 674}, {"name": "13 Style Let's Go Brandon Adjustable Hat FJB Hat Joe Biden Baseball Cap One Size", "free_returns": true, "items_sold": null, "items_status": "Brand New", "items_shipping": 0, "price": 1499}, {"name": "Wool Herringbone Newsboy Gatsby Cap Ivy Hat Golf Mens Flat Cabbie Stripe", "free_returns": true, "items_sold": 1511, "items_status": "Brand New", "items_shipping": null, "price": 1399}, {"name": "Beanie Hat Cap Cuff Plain Knit Ski Skull  Winter Warm Slouchy Men Women Unisex", "free_returns": true, "items_sold": null, "items_status": "Brand New", "items_shipping": 0, "price": 598}, {"name": "Balaclava Ski Mask 1 hole Full Face Beanie Winter Hat Cap Fleece Trapper Outdoor", "free_returns": true, "items_sold": null, "items_status": "Brand New", "items_shipping": null, "price": 995}, {"name": "Duck Mesh Summer Gatsby Cap Mens Ivy Hat Golf Driving Sun Flat Cabbie Newsboy", "free_returns": true, "items_sold": null, "items_status": "Brand New", "items_shipping": 0, "price": 898}, {"name": "Boonie Bucket Hat Fishing Hunting Outdoor Summer Fisherman Cap Unisex", "free_returns": false, "items_sold": 139, "items_status": "Brand New", "items_shipping": null, "price": 599}, {"name": "", "free_returns": false, "items_sold": null, "items_status": null, "items_shipping": null, "price": null}, {"name": "Snapback Baseball Cap Hat Hip-Hop Men Army Adjustable Hats Flat Trucker CS ", "free_returns": true, "items_sold": null, "items_status": "Brand New", "items_shipping": null, "price": 895}, {"name": "Solid Cotton Gatsby Cap Mens Ivy Hat Golf Driving Summer Sun Flat Cabbie Newsboy", "free_returns": false, "items_sold": 26, "items_status": "Brand New", "items_shipping": 399, "price": 899}, {"name": "Women's Men Knit Slouchy Baggy Beanie Oversize Winter Hat Ski Fleece Slouchy Cap", "free_returns": true, "items_sold": null, "items_status": "Brand New", "items_shipping": null, "price": 799}, {"name": "Mens Womens Winter Baggy Slouchy Knit Warm Beanie Hat and Scarf Ski Skull Cap ", "free_returns": true, "items_sold": null, "items_status": "Brand New", "items_shipping": null, "price": 949}, {"name": "Carhartt\u00ae Cotton Canvas Cap 103938", "free_returns": true, "items_sold": null, "items_status": "Brand New", "items_shipping": 0, "price": 1790}, {"name": "Mens Hat Ribbed Solid Plain Knit Ski Cap Warm Beanie Skull Winter Cuff Hats US", "free_returns": true, "items_sold": null, "items_status": "Brand New", "items_shipping": 0, "price": 695}, {"name": "Trucker Hat Foam Mesh Baseball Cap Adjustable Snapback Solid Plain Men Hats Flat", "free_returns": true, "items_sold": 1982, "items_status": "Brand New", "items_shipping": null, "price": 795}, {"name": "Winter Warm Knit Hat Scarf Set Men Women Kids Ear Head Neck Cover Ski Beanie Cap", "free_returns": false, "items_sold": null, "items_status": "Brand New", "items_shipping": 0, "price": 1089}, {"name": "Plain Fitted Baseball Cap Curved Visor Solid Blank Color Caps Hat Hats - 9 SIZES", "free_returns": false, "items_sold": 208, "items_status": "Brand New", "items_shipping": 0, "price": 999}, {"name": "Bill Visor Cuff Beanie Knit Cap Hat Ski Thick Brim Warm Winter Unisex US MADE", "free_returns": true, "items_sold": 652, "items_status": "Brand New", "items_shipping": null, "price": 875}, {"name": "Military 100% Wool Knit Winter Hat Wool Watch Cap USA Made", "free_returns": true, "items_sold": 293, "items_status": "Brand New", "items_shipping": 0, "price": 1099}, {"name": "Oatmeal Ragg Wool Hat Knitted Outdoor Military Winter Cap", "free_returns": true, "items_sold": 354, "items_status": "Brand New", "items_shipping": 0, "price": 1199}, {"name": "Black Military Issue Wool Watch Cap 100% Wool Skiing Beanie Hat Rothco 8492", "free_returns": false, "items_sold": 0, "items_status": "Brand New", "items_shipping": 0, "price": 899}, {"name": "Mens Baseball Cap Washed Cotton Polo Style Caps Plain Adjustable Dad Hat Womens", "free_returns": true, "items_sold": null, "items_status": "Brand New", "items_shipping": 0, "price": 789}, {"name": "Mens Snapback Hat Cotton Mesh Solid Flat Brim Style Baseball Cap Trucker Visor ", "free_returns": true, "items_sold": null, "items_status": "Brand New", "items_shipping": 0, "price": 895}, {"name": "Womens Plain Baseball Cap Adjustable Solid Hat Polo Style Strapback Ballcap", "free_returns": true, "items_sold": null, "items_status": "Brand New", "items_shipping": 0, "price": 649}, {"name": "Baseball Cap for Men Tactical Army Cotton Dad Hat USA American Flag Caps Trucker", "free_returns": true, "items_sold": null, "items_status": "Brand New", "items_shipping": 0, "price": 1099}, {"name": "Trucker Hat Mesh Baseball Cap Snapback Adjustable Plain Solid Blank Hip Hop Men", "free_returns": true, "items_sold": 1302, "items_status": "Brand New", "items_shipping": null, "price": 795}, {"name": "Cuff Beanie Knit Hat Cap Slouchy Skull Ski Men Women Plain Winter Warm Hats", "free_returns": false, "items_sold": 276, "items_status": "Brand New", "items_shipping": 0, "price": 725}, {"name": "Beanie Plain Knit Ski Cap Hat Skull Warm Winter Colors Unisex Men Woman Beany ", "free_returns": true, "items_sold": null, "items_status": "Brand New", "items_shipping": null, "price": 830}, {"name": "New Era Mesh Snapback Hat Original Fit Trucker Cap 9FIFTY Blank Flat Brim 950", "free_returns": false, "items_sold": null, "items_status": "Brand New", "items_shipping": 0, "price": 1550}, {"name": "Top Level Plain Polyester Fitted Size Baseball Cap Hat 10 sizes Fitted Hat", "free_returns": false, "items_sold": 316, "items_status": "Brand New", "items_shipping": null, "price": 899}, {"name": "One 1 Hole Ski Full Face Mask Winter Cap Balaclava Hood Beanie Tactical Mask hat", "free_returns": true, "items_sold": 1590, "items_status": "Brand New", "items_shipping": null, "price": 975}, {"name": "Mexican Mexico Hat Federal Metallic Gold Logo Snapback Flat Bill Baseball Cap", "free_returns": true, "items_sold": 496, "items_status": "Brand New", "items_shipping": null, "price": 1585}, {"name": "Mens Womens Casual Baseball Cap Caps adjustable Running Golf Summer Baseball Hat", "free_returns": false, "items_sold": null, "items_status": "Brand New", "items_shipping": 0, "price": 1399}, {"name": "New Authentic Nike Heritage-86-Dri-Fit-Hat - Adjustable Swoosh on Front Cap", "free_returns": true, "items_sold": 2391, "items_status": "Brand New", "items_shipping": null, "price": 1995}, {"name": "Mens Baseball Cap USA American Flag Hat Adjustable Tactical Military Caps Army", "free_returns": true, "items_sold": null, "items_status": "Brand New", "items_shipping": 0, "price": 889}, {"name": "CC C.C Beanie New Women Slouchy Knit Oversized Thick Cap Hat Unisex Slouch Color", "free_returns": true, "items_sold": 666, "items_status": "Brand New", "items_shipping": 0, "price": 899}, {"name": "Snapback Hat Hip-Hop Baseball Cap for Men One Size Adjustable Hats Flat Bill ", "free_returns": true, "items_sold": null, "items_status": "Brand New", "items_shipping": 0, "price": 797}, {"name": "Trucker Hat Cotton Mesh Solid Washed Polo Style Baseball Cap Visor Summer Mens", "free_returns": true, "items_sold": null, "items_status": "Brand New", "items_shipping": 0, "price": 795}, {"name": "Classic Quality Bucket Hat 100% Cotton Size S/M ~ L/XL Summer Fisherman Hat Cap", "free_returns": false, "items_sold": null, "items_status": "Brand New", "items_shipping": 0, "price": 999}, {"name": "MEXICAN Hat MEXICO Federal Logo State Embroidery Snapback Flat Bill Baseball Cap", "free_returns": true, "items_sold": 710, "items_status": "Brand New", "items_shipping": null, "price": 1285}, {"name": "Cabbie Newsboy Gatsby Cap Mens Ivy Hat Golf Driving Summer Sun Flat", "free_returns": true, "items_sold": 931, "items_status": "Brand New", "items_shipping": null, "price": 1499}, {"name": "Men Winter Warm Hat Knit Visor Beanie Fleece Lined Billed Beanie with Brim Cap", "free_returns": false, "items_sold": null, "items_status": "Brand New", "items_shipping": 0, "price": 1022}, {"name": "Baseball Cap Corduroy Cord Hat Classic Snapback Adjustable Plain Solid Flat Men", "free_returns": true, "items_sold": 0, "items_status": "Brand New", "items_shipping": null, "price": 995}, {"name": "Tactical Warm Winter Fleece Watch Cap Military Beanie Skull Hat for Men Women", "free_returns": true, "items_sold": null, "items_status": "Brand New", "items_shipping": 0, "price": 798}, {"name": "WOOL Watch Cap MADE IN USA Government Issue USGI Navy USMC Army USCG USAF Beanie", "free_returns": true, "items_sold": 464, "items_status": "Brand New", "items_shipping": 0, "price": 979}, {"name": "Ribbed Thick Beanie Plain Knit Cuff Ski Cap Skull Hat Warm Solid Color Winter", "free_returns": true, "items_sold": 612, "items_status": "Brand New", "items_shipping": null, "price": 894}, {"name": "Usa300 #fjb Joe Biden Hat Let's Go Brandon Baseball Hat Cap Adjustable Hat", "free_returns": false, "items_sold": null, "items_status": "Brand New", "items_shipping": 0, "price": 1499}, {"name": "Winter Warm Face Mask Baseball Cap Trooper Russian Aviator Bomber Hat W/ Gloves", "free_returns": true, "items_sold": null, "items_status": "Brand New", "items_shipping": 0, "price": 1599}, {"name": " 100% Cotton KUFI Crochet Beanie Skull Cap Knit Hat Men Women 12 Colors NEW 632 ", "free_returns": false, "items_sold": null, "items_status": "Brand New", "items_shipping": 0, "price": 999}, {"name": "Under Armour Men's UA Blitzing 3.0 Athletic Cap - 1305036", "free_returns": true, "items_sold": null, "items_status": "Brand New", "items_shipping": 0, "price": 1695}, {"name": "New Era 39Thirty Cap Stretch Cotton Authentic Fitted NE1000 Hat (Multi Colors)", "free_returns": false, "items_sold": 315, "items_status": "Brand New", "items_shipping": null, "price": 1387}, {"name": "CALI Baseball Cap Bandana Paisley Snapback Adjustable Hat Hip Hop Flat Bill Men", "free_returns": true, "items_sold": 24, "items_status": "Brand New", "items_shipping": null, "price": 1295}, {"name": "WHISKEY 100% LEATHER Men Gatsby Cap Newsboy Ivy Hat Golf Driving Flat NWT S-3XL", "free_returns": false, "items_sold": 702, "items_status": "Brand New", "items_shipping": 390, "price": 1200}, {"name": "Short Beanie Plain Knit Hat Winter Solid Cuff Cap Slouchy Skull Ski Men Woman", "free_returns": true, "items_sold": 1008, "items_status": "Brand New", "items_shipping": null, "price": 795}, {"name": "New Era Trucker Snapback Mesh Back Hat Adjustable Cap 9FORTY 940", "free_returns": true, "items_sold": null, "items_status": "Brand New", "items_shipping": 0, "price": 1399}, {"name": "PUMA Men's Classic Dad Cap", "free_returns": true, "items_sold": 0, "items_status": "Brand New", "items_shipping": 0, "price": 999}, {"name": "Stylish Camouflage Embroidered MLB Football Hat Flat Brim Snapback Baseball Cap", "free_returns": false, "items_sold": null, "items_status": "Brand New", "items_shipping": 0, "price": 1299}, {"name": "MEXICAN Hat Snapback MEXICO Federal Logo Embroidered Baseball Cap- Black/Gold", "free_returns": true, "items_sold": 676, "items_status": "Brand New", "items_shipping": null, "price": 1285}, {"name": "Fashion Under Armour Embroidered  Sun Hat Baseball Cap Stretch Fit CapFashion Un", "free_returns": false, "items_sold": null, "items_status": "Brand New", "items_shipping": 0, "price": 1266}, {"name": "Leather Snapback Hat Hip Hop Baseball Cap Trucker Mesh Solid Plain Flat Bill Men", "free_returns": true, "items_sold": 410, "items_status": "Brand New", "items_shipping": null, "price": 1899}, {"name": "adidas Originals Sideline Four-Panel Hat Men's", "free_returns": true, "items_sold": 0, "items_status": "Brand New", "items_shipping": 0, "price": 1400}, {"name": "New Era 39THIRTY Mesh Back Flex Stretch Hat Blank Cap", "free_returns": true, "items_sold": 119, "items_status": "Brand New", "items_shipping": 0, "price": 1495}, {"name": "New 100% Genuine Real Lambskin Leather Baseball Cap Hat Trucker Sports Visor", "free_returns": false, "items_sold": 1945, "items_status": "Brand New", "items_shipping": 290, "price": 890}, {"name": "Carhartt Ashland Hat Flat Bill Cap - Adjustable - Choose Color - New w/ Tags", "free_returns": false, "items_sold": null, "items_status": "Brand New", "items_shipping": 0, "price": 1895}, {"name": "Decky Beanies GI Caps Hats Visor Ski Thick Warm Winter Skully Unisex", "free_returns": true, "items_sold": 1121, "items_status": "Brand New", "items_shipping": null, "price": 895}, {"name": "Warm Winter Knit Cuff Beanie Cap Fisherman Watch Cap Daily Ski Hat Skully", "free_returns": false, "items_sold": 658, "items_status": "Brand New", "items_shipping": 0, "price": 1199}, {"name": "Baseball Cap USA Flag American Mens Hat Detachable Patch Mesh Tactical Army Caps", "free_returns": true, "items_sold": null, "items_status": "Brand New", "items_shipping": 0, "price": 999}, {"name": "Baseball Cap Adjustable Embroidered LA Los Angeles Latter Sports Hat For Unisex", "free_returns": false, "items_sold": null, "items_status": "Brand New", "items_shipping": 199, "price": 999}, {"name": "Bass Pro Shops Hat Outdoor Fishing Baseball Trucker Mesh Cap Adjustable SnapBack", "free_returns": true, "items_sold": 225, "items_status": "New (Other)", "items_shipping": 0, "price": 1695}, {"name": "Mororock 30Colors Beanie Thicken Warm Cuff Plain Knit Ski Cap Men Women Acrylic ", "free_returns": true, "items_sold": 675, "items_status": "Brand New", "items_shipping": 0, "price": 677}, {"name": "Baseball Cap Two Tone Snapback Adjustable One Size Hat Flat Bill Blank 6 Panels", "free_returns": true, "items_sold": null, "items_status": "Brand New", "items_shipping": 0, "price": 894}, {"name": "Men Aviator Bomber Face Mask Hat Fur Ear Flap Cap Winter Ski Trooper Trapper Hat", "free_returns": true, "items_sold": 55, "items_status": "Brand New", "items_shipping": 0, "price": 1099}, {"name": "", "free_returns": false, "items_sold": null, "items_status": null, "items_shipping": null, "price": null}, {"name": "Mens Adjustable Cotton Baseball Caps Dad Hat Washed Ball Cap for Men and Women", "free_returns": true, "items_sold": null, "items_status": "Brand New", "items_shipping": 0, "price": 702}, {"name": "Baseball Cap Men/Women Sunshade Adjustable Outdoor Holiday Travel Casual Hat ", "free_returns": false, "items_sold": 158, "items_status": "Brand New", "items_shipping": 0, "price": 999}, {"name": "Men's Women's Knitted Skull Slouchy Baggy Beanie Oversize Winter Hat Ski Cap", "free_returns": true, "items_sold": 160, "items_status": "New (Other)", "items_shipping": null, "price": 699}, {"name": "Trucker Hat Foam Mesh Snapback Adjustable Baseball Cap Solid Blank Curved Men", "free_returns": true, "items_sold": null, "items_status": "Brand New", "items_shipping": 0, "price": 775}, {"name": "Trump 2024 Save America Again Flag Embroidered Cap Black", "free_returns": false, "items_sold": null, "items_status": "Brand New", "items_shipping": null, "price": 1299}, {"name": "Baseball Cap Cotton Solid Plain men women Ball Hat Dad Hat Polo Washed Ball PC", "free_returns": true, "items_sold": 2191, "items_status": "Brand New", "items_shipping": null, "price": 875}, {"name": "Cadet Hat Army Castro Baseball Cap Military Adjustable Distressed Plain Men Hats", "free_returns": true, "items_sold": 269, "items_status": "Brand New", "items_shipping": null, "price": 895}, {"name": "Army Cadet Military Patrol Cap Castro Hat Men Women Golf Driving Summer Baseball", "free_returns": false, "items_sold": 119, "items_status": "New (Other)", "items_shipping": 199, "price": 699}, {"name": "Face Mask Ski Mask Winter Cap 3 Hole Balaclava Beanie Hat Hood Tactical Warm Men", "free_returns": true, "items_sold": null, "items_status": "Brand New", "items_shipping": 0, "price": 796}, {"name": "U.S. ARMY Hat VETERAN ARMY Embroidered Military Officially Licensed Baseball Cap", "free_returns": true, "items_sold": null, "items_status": "Brand New", "items_shipping": null, "price": 1385}, {"name": "Tactical Boonie Hat Military Camo Bucket Wide Brim Sun Fishing Bush Booney Cap", "free_returns": true, "items_sold": 84, "items_status": "Brand New", "items_shipping": 0, "price": 1299}, {"name": "Genuine Military 100% Wool Watch Cap Beanie Cap USA MADE", "free_returns": true, "items_sold": 1034, "items_status": "Brand New", "items_shipping": 250, "price": 699}, {"name": "Carhartt Acrylic Beanie Knit Men's Stocking Cap Warm Winter Hat Authentic", "free_returns": false, "items_sold": 323, "items_status": "Brand New", "items_shipping": 0, "price": 1999}, {"name": "Cotton Cap Baseball Caps Hat Adjustable Polo Style Washed Plain Solid Dad PC", "free_returns": true, "items_sold": 655, "items_status": "New (Other)", "items_shipping": null, "price": 799}, {"name": "Men\u2019s Striped Ribbed Slouchy Knit Beanie Winter Hat Warm Work Cap Soft Toboggan", "free_returns": true, "items_sold": null, "items_status": "Brand New", "items_shipping": 0, "price": 749}, {"name": "1-2 Pack 3 Hole Full Face Mask Ski Cap Winter Balaclava Hood Beanie Tactical Hat", "free_returns": true, "items_sold": null, "items_status": "Brand New", "items_shipping": 0, "price": 899}, {"name": "2021 New Fashion Baseball Hat Cap Let's Go Brandon Sticker Pattern Hat #FJB", "free_returns": false, "items_sold": null, "items_status": "Brand New", "items_shipping": 0, "price": 1399}, {"name": "Cuff Beanie Plain Knit Hat Winter Solid Cap Slouchy Skull Ski Warm Men Women", "free_returns": true, "items_sold": null, "items_status": "Brand New", "items_shipping": null, "price": 695}, {"name": "Trucker Hat Mesh Baseball Snapback Cap Meshback Flat Visor Plain Hip Hop Mens ", "free_returns": true, "items_sold": 149, "items_status": "Brand New", "items_shipping": null, "price": 995}, {"name": "Unisex 100% Cotton Bucket Hat Fishing Camping Safari Boonie Sun Brim Summer Cap", "free_returns": true, "items_sold": null, "items_status": "Brand New", "items_shipping": null, "price": 1048}, {"name": "Boonie Bucket Hat Cap 100% Cotton Fishing Hunting Safari Summer Military Men Sun", "free_returns": true, "items_sold": null, "items_status": "Brand New", "items_shipping": null, "price": 1095}, {"name": "WK Wool Tweed Plaid Ivy Herringbone Winter Cap Hat Golf Flat Cabbie Newsboy", "free_returns": true, "items_sold": 916, "items_status": "Brand New", "items_shipping": null, "price": 1395}, {"name": "Women's Men Knit Slouchy Baggy Beanie Oversize Winter Hat Ski Slouchy Cap C", "free_returns": true, "items_sold": null, "items_status": "Brand New", "items_shipping": null, "price": 785}, {"name": "Let's Go Brandon Premium Baseball Cap FJB USA Trending Beanies Caps Trucker Hats", "free_returns": true, "items_sold": null, "items_status": "Brand New", "items_shipping": 0, "price": 1499}, {"name": " New Goorin Bros Animal Farm Trucker Mesh Baseball Ha t Snapback  Cap Hip Hop Me", "free_returns": false, "items_sold": null, "items_status": "Brand New", "items_shipping": 0, "price": 810}, {"name": "USA Flag Hat Detachable Patch Tactical Operator Micro Mesh Military Baseball Cap", "free_returns": true, "items_sold": 371, "items_status": "Brand New", "items_shipping": null, "price": 1285}, {"name": "DECKY RP1 MENS PLAIN HAT FLAT BILL BASEBALL HATS CASUAL FITTED CAP BASIC CAPS", "free_returns": true, "items_sold": null, "items_status": "Brand New", "items_shipping": null, "price": 995}, {"name": "V-Adjustable Solid Leather Classic Unisex Trucker Baseball Cap Plain Blank Hat ", "free_returns": true, "items_sold": 456, "items_status": "Brand New", "items_shipping": null, "price": 1699}, {"name": "Mens Womens Unisex Winter Warm Slouchy Fleece Beanie Hat Skull Ski Knit Cap New", "free_returns": true, "items_sold": null, "items_status": "Brand New", "items_shipping": null, "price": 749}, {"name": "Baseball Cap Plain Snapback Adjustable One Size Trucker Hat New Flat Bill Black", "free_returns": true, "items_sold": null, "items_status": "Brand New", "items_shipping": 0, "price": 895}, {"name": "Brimless Docker Cap Hats with Adjustable Strap | Retro No Visor Cap", "free_returns": false, "items_sold": 35, "items_status": "Brand New", "items_shipping": 0, "price": 1274}, {"name": "Mens Mini Short Fisherman Beanie Hat Winter Ribbed Docker Warm Knitted Skull Cap", "free_returns": false, "items_sold": 133, "items_status": "Brand New", "items_shipping": 99, "price": 799}, {"name": "Carhartt  Acrylic Watch Beanie Winter Knit Warm Cap Hat Mens Womens", "free_returns": true, "items_sold": null, "items_status": "Brand New", "items_shipping": 0, "price": 1119}, {"name": "Dyed Washed Cotton New Plain Polo Style Baseball Ball Cap Hat Dad 2 Two Tone", "free_returns": true, "items_sold": 449, "items_status": "Brand New", "items_shipping": 0, "price": 995}, {"name": "Trucker Hat Foam Mesh Back Baseball Cap Snapback Adjustable Plain Solid Men Caps", "free_returns": true, "items_sold": 1330, "items_status": "Brand New", "items_shipping": null, "price": 795}, {"name": "BASEBALL CAP Solid Genuine Black Leather Adjustable Motorcycle Biker Mens Womens", "free_returns": true, "items_sold": null, "items_status": "Brand New", "items_shipping": 0, "price": 1379}, {"name": "Condor Tactical Microfleece Watch Cap", "free_returns": false, "items_sold": 24, "items_status": "Brand New", "items_shipping": 0, "price": 895}, {"name": "Carhartt Men Women Acrylic Watch Hat Winter Beanie Knit Cap Warm Stocking Hats", "free_returns": false, "items_sold": 22, "items_status": "Brand New", "items_shipping": 0, "price": 1085}, {"name": "VOBOOM Mens Solid Cotton Gatsby Cap Ivy Hat Golf Driving Flat Cabbie Newsboy New", "free_returns": true, "items_sold": 29, "items_status": "Brand New", "items_shipping": 199, "price": 699}, {"name": "THICK Ribbed Beanie Knit Ski Cap Skull Hat Warm Solid Color Winter Cuff Blank", "free_returns": false, "items_sold": 2136, "items_status": "Brand New", "items_shipping": 0, "price": 1295}, {"name": "Solid Plain Beanie Hat Ski Cap Skull Knit Cuff Warm Slouchy Unisex Pick Colors* ", "free_returns": true, "items_sold": 861, "items_status": "Brand New", "items_shipping": 100, "price": 399}, {"name": "Balaclava Face Mask UV Protection Ski Sun Hood Tactical Masks for Men Women", "free_returns": true, "items_sold": null, "items_status": "Brand New", "items_shipping": 0, "price": 899}, {"name": "Men's Womens Knit Baggy Beanie Winter Warm Cashmere Hat Ski Slouchy Thick Cap", "free_returns": false, "items_sold": null, "items_status": "Brand New", "items_shipping": 0, "price": 911}, {"name": "Balaclava Face Mask UV Protection Ski Sun Hood Tactical Mask for Men Women Black", "free_returns": true, "items_sold": null, "items_status": "Brand New", "items_shipping": 0, "price": 899}, {"name": "Fisherman Beanie Thermal Cotton Watch Cap Winter Hat Skull Cap Ski", "free_returns": false, "items_sold": 386, "items_status": "Brand New", "items_shipping": 0, "price": 975}, {"name": "Beanie Plain Cuffed Cuff Solid Knit Winter Cap Hat Ski Men Woman ", "free_returns": false, "items_sold": 169, "items_status": "New (Other)", "items_shipping": null, "price": 695}, {"name": "1pc Cotton Biker SKULL CAP Motorcycle Bandana Head Wrap Du Doo Dew Rag Black Hat", "free_returns": true, "items_sold": null, "items_status": "Brand New", "items_shipping": 0, "price": 679}, {"name": "New Beanie Women Men Acrylic Watch Hat Carhartt Winter Warm Knit Cap Unisex Hat", "free_returns": false, "items_sold": null, "items_status": "Brand New", "items_shipping": 0, "price": 1499}, {"name": "Visor Sun Plain Hat Sports Cap Colors Golf Tennis Beach Adjustable Summer", "free_returns": true, "items_sold": 1560, "items_status": "Brand New", "items_shipping": null, "price": 785}, {"name": "New 100% Genuine Real Lambskin Leather Baseball Cap Hat Sport Visor 12 COLORS", "free_returns": false, "items_sold": 688, "items_status": "Brand New", "items_shipping": 290, "price": 890}, {"name": "NEW Retro Embroidered Logo Flat Brim HipHop Hat Snapback Sports Sun Basebal Cap", "free_returns": false, "items_sold": null, "items_status": "New (Other)", "items_shipping": 0, "price": 1399}, {"name": "Goat Baseball Cap Embroidered Cotton Adjustable Dad Hat", "free_returns": false, "items_sold": null, "items_status": "New (Other)", "items_shipping": 0, "price": 1599}, {"name": "Carhartt Fleece Beanie Stocking Cap Warm Winter Hat A207", "free_returns": false, "items_sold": 20, "items_status": "Brand New", "items_shipping": 0, "price": 1650}, {"name": "Embroidered KTM MOTO GP Hat Motorcycle Baseball Cap Snapback Racing Caps", "free_returns": false, "items_sold": null, "items_status": "Brand New", "items_shipping": 0, "price": 1299}, {"name": "DALIX Baseball Cap Dad Hat Plain Men Women Cotton Adjustable Blank Unstructured", "free_returns": true, "items_sold": null, "items_status": "Brand New", "items_shipping": 350, "price": 349}, {"name": "Bucket Hat Cap Cotton Fishing Boonie Brim visor Sun Safari Summer Men Camping", "free_returns": true, "items_sold": 1314, "items_status": "Brand New", "items_shipping": null, "price": 874}, {"name": "Mercedes-Benz\u00b2 Logo AMG Car Cap Sport Baseball Hat outdoor Adjustab", "free_returns": false, "items_sold": 116, "items_status": "New (Other)", "items_shipping": 0, "price": 1399}, {"name": "Mcguire Gear 100% Wool Watch Cap Beanie - Military Style Made in USA, (One Size)", "free_returns": true, "items_sold": 171, "items_status": "Brand New", "items_shipping": 0, "price": 999}, {"name": "Mens Summer Bucket Cap Cowboy Fedora Hat Wide Brim Linen Mesh Fishing Beach Sun", "free_returns": false, "items_sold": null, "items_status": "Brand New", "items_shipping": null, "price": 999}, {"name": "New Under Armour Strapback Golf Baseball Cap Embroidered Women Men Hat US", "free_returns": false, "items_sold": 31, "items_status": "Brand New", "items_shipping": 100, "price": 1098}, {"name": "Men's adidas Creator 2 Trefoil Beanie Winter Cap Hat Black Stealth Aero Ready", "free_returns": false, "items_sold": null, "items_status": "Brand New", "items_shipping": null, "price": 2247}, {"name": "Trump 2024 The Sequel Embroidered Mesh Cap Red", "free_returns": false, "items_sold": null, "items_status": "Brand New", "items_shipping": null, "price": 999}, {"name": "Men Women Sun Protection Hat Neck Face Flap Cap Wide Brim Hot Fishing Bucket Hat", "free_returns": true, "items_sold": null, "items_status": "Brand New", "items_shipping": 0, "price": 1199}, {"name": "Moisture Sweat Wicking Cooling Bald Dome Skull Cap Helmet Liner Sport Beanie Hat", "free_returns": true, "items_sold": null, "items_status": "Brand New", "items_shipping": null, "price": 686}, {"name": "", "free_returns": false, "items_sold": null, "items_status": null, "items_shipping": null, "price": null}, {"name": "Suede Hat Baseball Cap Classic Strapback Adjustable Solid Plain Curved Blank Men", "free_returns": true, "items_sold": 193, "items_status": "Brand New", "items_shipping": null, "price": 995}, {"name": "Moisture Sweat Wicking Cooling Bald Dome Skull Cap Helmet Liner Sport Beanie Hat", "free_returns": true, "items_sold": null, "items_status": "Brand New", "items_shipping": null, "price": 686}, {"name": "1-2PCS 3 in1 Thermal Fur Lined Trapper Bomber Hat With Ear Flap Baseball Ski Cap", "free_returns": true, "items_sold": null, "items_status": "Brand New", "items_shipping": 0, "price": 799}, {"name": "Beanie Hat Women Men Plain Knit Ski Cap Warm Slouchy Baggy Skull Spring Winter", "free_returns": true, "items_sold": null, "items_status": "Brand New", "items_shipping": null, "price": 695}, {"name": "FBI Hat Baseball Cap Adjustable Embroidered Black Hat Headwear", "free_returns": false, "items_sold": null, "items_status": "Brand New", "items_shipping": 0, "price": 785}, {"name": " Baseball Cap Ball Dad Hat Adjustable Plain Solid Cotton Polo Washed Mens Womens", "free_returns": true, "items_sold": 701, "items_status": "Brand New", "items_shipping": null, "price": 795}, {"name": " Solid Cotton Gatsby Cap Mens Ivy Hat Golf Driving Sun Flat Cabbie Newsboy", "free_returns": true, "items_sold": null, "items_status": "New (Other)", "items_shipping": 299, "price": 629}, {"name": "\"Let's Go Brandon\" Embroidered Hat Ball Cap Many Colors New!", "free_returns": false, "items_sold": null, "items_status": "Brand New", "items_shipping": 0, "price": 1495}, {"name": "Trump 2024 Camo Hat Cap Save America Again Donald MAGA KAG Take America Back", "free_returns": true, "items_sold": null, "items_status": "Brand New", "items_shipping": 0, "price": 698}, {"name": "Unisex Women Men Velvet Durag Hat Cap Premium Design Doo Rag Wave Bicycle Dance", "free_returns": false, "items_sold": null, "items_status": "Brand New", "items_shipping": null, "price": 699}, {"name": "Let's Go Brandon 2135 Anti Biden Embroidered Adjustable Trump 2024 MAGA Cap Hat", "free_returns": false, "items_sold": 80, "items_status": "Brand New", "items_shipping": 0, "price": 1599}, {"name": "MEXICAN Hat MEXICO Eagle Federal Logo Snapback Flat Bill Cotton Baseball Cap", "free_returns": true, "items_sold": null, "items_status": "Brand New", "items_shipping": null, "price": 1385}, {"name": "Mexican Hat Snapback Hecho En Mexico Eagle Aguila Flag Flat Bill Baseball Cap", "free_returns": true, "items_sold": null, "items_status": "Brand New", "items_shipping": null, "price": 1385}, {"name": "NTG Navy ARMY Digital Camo USA American Flag Tactical Baseball Hat Cap", "free_returns": false, "items_sold": null, "items_status": "Brand New", "items_shipping": 0, "price": 988}, {"name": "5 Panel Solid Camo Strap-back Adjustable Leather Strap Cap Hat JLGUSA", "free_returns": false, "items_sold": null, "items_status": "Brand New", "items_shipping": 0, "price": 1199}, {"name": "Men's 100% Winter Wool Patch Plaids Snap Newsboy Drivers Cabbie Cap Hat", "free_returns": false, "items_sold": 41, "items_status": "Brand New", "items_shipping": 0, "price": 1529}, {"name": "Men Women Winter Warm Hats Cap Fleece Ski Snow Mask Caps Hood Neck Hat Balaclava", "free_returns": false, "items_sold": null, "items_status": "Brand New", "items_shipping": null, "price": 847}, {"name": "Custom Embroidery Beanie Personalized Embroidered Beanie Knit Cap w/Cuff Black", "free_returns": false, "items_sold": 598, "items_status": "Brand New", "items_shipping": 0, "price": 1499}, {"name": "Breathable Men's Sport Cap Fast Dry Baseball Cap Golf Ball Dad Hat Adjustable", "free_returns": true, "items_sold": 78, "items_status": "Brand New", "items_shipping": null, "price": 795}, {"name": "NWT 100% LEATHER Men Gatsby Cap Newsboy Ivy Hat Golf Driving Flat Cabbie S-3XL", "free_returns": false, "items_sold": 667, "items_status": "Brand New", "items_shipping": 390, "price": 1200}, {"name": "Carhartt Odessa Cap - Front Logo Hat 100289", "free_returns": true, "items_sold": null, "items_status": "Brand New", "items_shipping": 0, "price": 1789}, {"name": "NIKE Heritage 86 Hat Adjustable Fit Cap Mens Hat 102699 New - Pick a Color", "free_returns": true, "items_sold": 64, "items_status": "Brand New", "items_shipping": 0, "price": 1895}, {"name": "BN Knit Slouchy Baggy Beanie Winter Hat Ski Solid Cap Skull Men Women Cuff", "free_returns": true, "items_sold": 372, "items_status": "Brand New", "items_shipping": null, "price": 845}, {"name": "Fashion Tesla Racing Sports Hat Adjustable Strap Baseball Cap Unisex Men Women", "free_returns": false, "items_sold": null, "items_status": "Brand New", "items_shipping": 0, "price": 899}, {"name": "New Realtree Edge 12 Inch Knit Outdoor Camouflage Beanie Camo Cap ", "free_returns": true, "items_sold": null, "items_status": "Brand New", "items_shipping": 0, "price": 1295}, {"name": "1pc Cotton Paisley SKULL CAP Du Rag Head Wrap Motorcycle Biker Dew Doo Bandana", "free_returns": true, "items_sold": null, "items_status": "Brand New", "items_shipping": 0, "price": 479}, {"name": "New Dickies Fleece Beanie Cap - Graphite Gray - One Size Fits All", "free_returns": false, "items_sold": 630, "items_status": "Brand New", "items_shipping": 0, "price": 599}, {"name": "UPS Embroidered Adjustable Cap Hat", "free_returns": false, "items_sold": null, "items_status": "Brand New", "items_shipping": 0, "price": 1599}, {"name": "MENS NEWSBOY CAP 100% COTTON TWILL GATSBY BERET DRIVING GOLF CABBIE SUMMER HATS", "free_returns": false, "items_sold": 0, "items_status": "Brand New", "items_shipping": 399, "price": 1499}, {"name": "Beanie Hat Mens Womens Plain Knit Ski Cap Warm Slouchy Skull Winter Cuff Thermal", "free_returns": true, "items_sold": null, "items_status": "Brand New", "items_shipping": 0, "price": 699}, {"name": "Winter Thermal Trapper Hat with Glasses Winter Cycling Windproof Ski Mask Cap", "free_returns": false, "items_sold": 0, "items_status": "Brand New", "items_shipping": 0, "price": 1576}, {"name": "L.O.G.A Plain Blank Solid Polyester Fitted Sized Flat Bill Cap Hat 9 Sizes", "free_returns": false, "items_sold": 117, "items_status": "Brand New", "items_shipping": null, "price": 999}, {"name": "FLEXFIT Classic KRYPTEK 6-Panel Fitted Camo Baseball Cap HAT S/M & L/XL New!", "free_returns": true, "items_sold": null, "items_status": "Brand New", "items_shipping": 0, "price": 1488}, {"name": "RapDom Military Camouflage Camo GI Beanies with Visor Knit Watch Caps Hats", "free_returns": true, "items_sold": 665, "items_status": "Brand New", "items_shipping": null, "price": 995}, {"name": "Flexfit Wooly Combed Cap FF6277", "free_returns": false, "items_sold": 23, "items_status": "Brand New", "items_shipping": 0, "price": 1259}, {"name": " Richardson 112 Trucker Hat", "free_returns": false, "items_sold": null, "items_status": "Brand New", "items_shipping": 0, "price": 1099}, {"name": "MEXICAN MEXICO Hat Hecho En Mexico Eagle Aguila Snapback Curved Baseball Cap", "free_returns": true, "items_sold": null, "items_status": "Brand New", "items_shipping": null, "price": 1245}, {"name": "Men Women Western Cowboy Wool Hat Wide Brim Cap Retro Cowgirl Unisex Riding Hat", "free_returns": false, "items_sold": null, "items_status": "Brand New", "items_shipping": 0, "price": 899}, {"name": "Baseball Hat (Dad hat/cap) - Solid Color - Strapback", "free_returns": true, "items_sold": null, "items_status": "Brand New", "items_shipping": 0, "price": 599}, {"name": "Baseball Cap Flame Embroidered Adjustable Hat Plain Solid Blank Curved Men Caps", "free_returns": true, "items_sold": null, "items_status": "Brand New", "items_shipping": null, "price": 895}, {"name": "Cable Knit Beanie Solid Cuffless Trendy Stretchy Winter Hat Ski Cap", "free_returns": false, "items_sold": 561, "items_status": "Brand New", "items_shipping": 0, "price": 999}, {"name": "Flexfit Wool Blend Cap FF6477", "free_returns": false, "items_sold": null, "items_status": "Brand New", "items_shipping": 0, "price": 1099}, {"name": "Men's Newsboy Button Top Ascot Ivy Cabbie Hat Gatsby Cap Plaid PU Leather", "free_returns": false, "items_sold": 154, "items_status": "Brand New", "items_shipping": 0, "price": 1299}, {"name": "Washed Cotton Gatsby Cap Mens Ivy Hat Golf Driving Summer Flat Cabbie Newsboy", "free_returns": true, "items_sold": 106, "items_status": "Brand New", "items_shipping": null, "price": 1375}, {"name": "Genuine Leather Flat Ivy Cap Men's Newsboy News Boy Gatsby Bonnet Cabbie Golf", "free_returns": true, "items_sold": 323, "items_status": "Brand New", "items_shipping": null, "price": 2249}, {"name": "Military Polar Fleece Beanie Watch Cap Cold Weather Skull Warm Winter Hat", "free_returns": true, "items_sold": 118, "items_status": "Brand New", "items_shipping": 0, "price": 899}, {"name": "Tactical Operator Cap Adjustable Military Contractor Army Patch Camo Hat", "free_returns": true, "items_sold": 169, "items_status": "Brand New", "items_shipping": 0, "price": 899}, {"name": "Military Hat Army Cadet Patrol Castro Cap Men Women Golf Driving Summer Castro", "free_returns": false, "items_sold": 753, "items_status": "Brand New", "items_shipping": 0, "price": 1199}, {"name": "YUPOONG Classic Twill DAD HAT Adjustable Strapback Baseball Cap New!", "free_returns": true, "items_sold": null, "items_status": "Brand New", "items_shipping": 0, "price": 1177}, {"name": "Unisex Carhartt Acrylic Watch Beanie Winter Knit Stocking Cap Warm Hat Mens Lady", "free_returns": false, "items_sold": 6, "items_status": "Brand New", "items_shipping": 0, "price": 1499}, {"name": "U.S. AIR FORCE Hat USAF Military Logo Embroidery Official Licensed Baseball Cap", "free_returns": true, "items_sold": null, "items_status": "Brand New", "items_shipping": null, "price": 1385}, {"name": "DECKY 7 Panel Cotton Snapbacks Snapback Flat Bill  Baseball Hats Cap Caps Unisex", "free_returns": true, "items_sold": 97, "items_status": "Brand New", "items_shipping": null, "price": 1295}, {"name": "NEW Columbia PFG Fish Flag Snapback Cap", "free_returns": false, "items_sold": null, "items_status": "Brand New", "items_shipping": 0, "price": 2275}, {"name": "Spandex Dome Cap Helmet Liner FootBall Biker Beanie Hat Head Black *Please Read*", "free_returns": false, "items_sold": 1305, "items_status": "Brand New", "items_shipping": 0, "price": 389}, {"name": "Winter Hat Aviator Russian Trooper Earflap Mens Womens Warm Snow Ski Mask Cap", "free_returns": true, "items_sold": 105, "items_status": "Brand New", "items_shipping": null, "price": 1055}, {"name": "Men's Everyday Cotton All Season Porkpie Boater Derby Fedora Sun Hat", "free_returns": false, "items_sold": 248, "items_status": "Brand New", "items_shipping": 0, "price": 1619}, {"name": " Winter Knit Jeep Cap 100% Wool GI Genuine Military Made in USA Rothco New ", "free_returns": true, "items_sold": 218, "items_status": "Brand New", "items_shipping": null, "price": 1099}, {"name": "Baseball Cap Snapback Hat Adjustable Classic Plain Solid Curved Visor Men Women", "free_returns": true, "items_sold": 432, "items_status": "Brand New", "items_shipping": null, "price": 795}, {"name": "Puma Bmw Motorsport Flatbrim Cap Mens     Cap Stretch", "free_returns": true, "items_sold": null, "items_status": "Brand New", "items_shipping": 0, "price": 1299}, {"name": "Nike Dri-FIT Swoosh Front Adjustable Strapback Dad Cap Authentic Men's Hat Golf", "free_returns": true, "items_sold": null, "items_status": "Brand New", "items_shipping": 0, "price": 1895}, {"name": "Fleece Beanie Sherpa Fleece Lined hat Cap Winter Cold Camo Solid", "free_returns": true, "items_sold": 83, "items_status": "Brand New", "items_shipping": null, "price": 1099}, {"name": "Military Issued USAF Patrol Cap-NEW", "free_returns": false, "items_sold": null, "items_status": "New (Other)", "items_shipping": 0, "price": 799}, {"name": "Baseball Cap Men/Women stripes Sunshade Adjustable Outdoor Travel Casual Hat", "free_returns": false, "items_sold": 0, "items_status": "Brand New", "items_shipping": 0, "price": 999}, {"name": "Chevrolet Logo Cap Adjustable Unisex Baseball Hat Summer Fashion  Baseball Cap", "free_returns": false, "items_sold": null, "items_status": "Brand New", "items_shipping": 0, "price": 908}]